LICENSE
README.md
ness/__init__.py
ness/cli.py
ness/datalake.py
ness-0.1.5.dist-info/entry_points.txt
ness-0.1.5.dist-info/LICENSE
ness-0.1.5.dist-info/WHEEL
ness-0.1.5.dist-info/METADATA
ness-0.1.5.dist-info/RECORD
