Metadata-Version: 2.1
Name: ness
Version: 0.1.5
Summary: A Python datalake client.
Home-page: https://github.com/postpayio/ness
License: MIT
Keywords: ness,datalake,s3,pandas
Author: Dani
Author-email: dani@postpay.io
Requires-Python: >=3.7.1,<4.0
Classifier: Development Status :: 2 - Pre-Alpha
Classifier: Environment :: Web Environment
Classifier: Intended Audience :: Developers
Classifier: Intended Audience :: Information Technology
Classifier: Intended Audience :: System Administrators
Classifier: License :: OSI Approved :: MIT License
Classifier: Operating System :: OS Independent
Classifier: Programming Language :: Python
Classifier: Programming Language :: Python :: 3
Classifier: Programming Language :: Python :: 3.10
Classifier: Programming Language :: Python :: 3.7
Classifier: Programming Language :: Python :: 3.8
Classifier: Programming Language :: Python :: 3.9
Classifier: Topic :: Internet
Classifier: Topic :: Internet :: WWW/HTTP
Classifier: Topic :: Internet :: WWW/HTTP :: HTTP Servers
Classifier: Topic :: Software Development
Classifier: Topic :: Software Development :: Libraries
Classifier: Topic :: Software Development :: Libraries :: Python Modules
Classifier: Topic :: Utilities
Classifier: Typing :: Typed
Requires-Dist: click (>=8.0.0)
Requires-Dist: pandas (>=0.18.1)
Project-URL: Repository, https://github.com/postpayio/ness
